llama_index/readers/whisper/__init__.py
llama_index/readers/whisper/base.py
llama_index_readers_whisper-0.3.0.dist-info/METADATA
llama_index_readers_whisper-0.3.0.dist-info/WHEEL
llama_index_readers_whisper-0.3.0.dist-info/licenses/LICENSE
llama_index_readers_whisper-0.3.0.dist-info/RECORD
