Metadata-Version: 2.4
Name: llama-index-readers-whisper
Version: 0.3.0
Summary: llama-index readers openai whisper integration
Author-email: Logan Markewich <logan@runllama.ai>
Maintainer: logan-markewich
License-Expression: MIT
License-File: LICENSE
Requires-Python: <4.0,>=3.9
Requires-Dist: llama-index-core<0.15,>=0.13.0
Requires-Dist: openai<3,>=1
